gketap/__init__.py
gketap/cli.py
gketap/core.py
gketap-1.0.2.dist-info/licenses/LICENSE
gketap-1.0.2.dist-info/METADATA
gketap-1.0.2.dist-info/WHEEL
gketap-1.0.2.dist-info/entry_points.txt
gketap-1.0.2.dist-info/top_level.txt
gketap-1.0.2.dist-info/RECORD
