Metadata-Version: 2.4
Name: gketap
Version: 1.0.2
Summary: A CLI tool to tap into GKE clusters via SSH tunnels
Home-page: https://github.com/drulacosmin/gketap
Author: Cosmin Drula
Classifier: Programming Language :: Python :: 3
Classifier: License :: OSI Approved :: MIT License
Requires-Python: >=3.7
License-File: LICENSE
Requires-Dist: click
Requires-Dist: pyyaml
Requires-Dist: psutil
Requires-Dist: rich
Dynamic: author
Dynamic: classifier
Dynamic: home-page
Dynamic: license-file
Dynamic: requires-dist
Dynamic: requires-python
Dynamic: summary
